pyefficiency.py
pyefficiency-1.1.dist-info/licenses/LICENSE
pyefficiency-1.1.dist-info/METADATA
pyefficiency-1.1.dist-info/WHEEL
pyefficiency-1.1.dist-info/top_level.txt
pyefficiency-1.1.dist-info/RECORD
