Metadata-Version: 2.4
Name: PyEfficiency
Version: 1.1
Summary: omg silly functions like binary searches and algorithmic functions!! :D
Author-email: Julia Al-Otoom <julia.alotoom.contact@gmail.com>
License: MIT License
Project-URL: Homepage, https://github.com/julia-alotoom/pyefficiency
Classifier: Programming Language :: Python :: 3
Classifier: Operating System :: OS Independent
Requires-Python: >=3.13
License-File: LICENSE
Dynamic: license-file
